<?xml version="1.0" encoding="UTF-8"?>
<window id="1119" type="window">
	<defaultcontrol always="true">50</defaultcontrol>
	<controls>
		<include>CommonBackground</include>
		<control type="group">
			<include>Animation.Common</include>
			<visible>!Window.IsActive(addoninformation)</visible>
			<control type="group">
				<left>90</left>
				<top>0</top>
				<control type="group">
	                <visible>Integer.IsGreater(Container(50).NumItems,0)</visible>
	                <control type="image">
	                	<left>0</left>
	                    <top>180</top>
	                    <width>550</width>
	                    <height>120</height>
	                    <visible>Control.HasFocus(50)</visible>
	                    <animation effect="fade" time="320" delay="200">Visible</animation>
	                    <animation effect="fade" time="50">Hidden</animation>
	                    <texture colordiffuse="$VAR[ColorHighlightVar]" border="5">listselect_fo.png</texture>
	                    <animation effect="slide" end="0,120" time="300" tween="cubic" easing="inout" condition="Integer.IsGreater(Container(50).Row,5)">Conditional</animation>
	                    <animation effect="slide" end="0,120" time="300" tween="cubic" easing="inout" condition="Integer.IsGreater(Container(50).Row,4)">Conditional</animation>
	                    <animation effect="slide" end="0,120" time="300" tween="cubic" easing="inout" condition="Integer.IsGreater(Container(50).Row,3)">Conditional</animation>
	                    <animation effect="slide" end="0,120" time="300" tween="cubic" easing="inout" condition="Integer.IsGreater(Container(50).Row,2)">Conditional</animation>
	                    <animation effect="slide" end="0,120" time="300" tween="cubic" easing="inout" condition="Integer.IsGreater(Container(50).Row,1)">Conditional</animation>
	                    <animation effect="slide" end="0,120" time="300" tween="cubic" easing="inout" condition="Integer.IsGreater(Container(50).Row,0)">Conditional</animation>
	                </control>
	            </control>
				<control type="panel" id="50">
					<left>0</left>
					<top>180</top>
					<width>550</width>
					<height>840</height>
					<onright condition="Integer.IsGreater(Container(51).NumItems,0)">51</onright>
					<onup>50</onup>
					<ondown>50</ondown>
					<viewtype label="535">list</viewtype>
					<scrolltime tween="quadratic" easing="out">200</scrolltime>
					<itemlayout height="120" width="550">
						<control type="image">
							<left>10</left>
							<top>10</top>
							<width>100</width>
							<height>100</height>
							<aspectratio>keep</aspectratio>
							<texture background="true">$INFO[ListItem.Icon]</texture>
						</control>
						<control type="label">
							<left>135</left>
							<top>3</top>
							<width>400</width>
							<height>70</height>
							<font>font30</font>
							<label>$INFO[ListItem.Label]</label>
						</control>
						<control type="label">
							<left>135</left>
							<top>52</top>
							<width>400</width>
							<height>60</height>
							<label>$INFO[ListItem.Label2]</label>
						</control>
					</itemlayout>
					<focusedlayout height="120" width="550">
						<control type="image">
							<left>10</left>
							<top>10</top>
							<width>100</width>
							<height>100</height>
							<aspectratio>keep</aspectratio>
							<texture background="true">$INFO[ListItem.Icon]</texture>
						</control>
						<control type="label">
							<left>135</left>
							<top>3</top>
							<width>400</width>
							<height>70</height>
							<font>font30</font>
							<label>$INFO[ListItem.Label]</label>
						</control>
						<control type="label">
							<left>135</left>
							<top>52</top>
							<width>400</width>
							<height>60</height>
							<label>$INFO[ListItem.Label2]</label>
						</control>
					</focusedlayout>
					<content>
						<item id="1">
							<label>$LOCALIZE[1037]</label>
							<label2>$INFO[Window(Home).Property(SkinHelper.TotalVideoAddons)] $LOCALIZE[31025]</label2>
							<icon>DefaultAddonVideo.png</icon>
							<property name="AppsTarget">videos</property>
							<property name="AppsContent">addons://sources/video/</property>
							<property name="AppsSortBy">lastused</property>
							<onclick>ActivateWindow(Videos,Addons,return)</onclick>
						</item>
						<item id="2">
							<label>$LOCALIZE[1038]</label>
							<label2>$INFO[Window(Home).Property(SkinHelper.TotalAudioAddons)] $LOCALIZE[31025]</label2>
							<icon>DefaultAddonMusic.png</icon>
							<property name="AppsTarget">music</property>
							<property name="AppsContent">addons://sources/audio/</property>
							<property name="AppsSortBy">lastused</property>
							<onclick>ActivateWindow(Music,Addons,return)</onclick>
						</item>
						<item id="3">
							<label>$LOCALIZE[1039]</label>
							<label2>$INFO[Window(Home).Property(SkinHelper.TotalPicturesAddons)] $LOCALIZE[31025]</label2>
							<icon>DefaultAddonPicture.png</icon>
							<property name="AppsTarget">pictures</property>
							<property name="AppsContent">addons://sources/image/</property>
							<property name="AppsSortBy">lastused</property>
							<onclick>ActivateWindow(Pictures,Addons,return)</onclick>
						</item>
						<item id="4">
							<label>$LOCALIZE[1043]</label>
							<label2>$INFO[Window(Home).Property(SkinHelper.TotalProgramAddons)] $LOCALIZE[31025]</label2>
							<icon>DefaultAddonProgram.png</icon>
							<property name="AppsTarget">programs</property>
							<property name="AppsContent">addons://sources/executable/</property>
							<property name="AppsSortBy">lastused</property>
							<onclick>ActivateWindow(Programs,Addons,return)</onclick>
						</item>
						<item id="5">
							<label>$LOCALIZE[20244]</label>
							<icon>DefaultIconAndroid.png</icon>
							<property name="AppsTarget">programs</property>
							<property name="AppsContent">androidapp://sources/apps/</property>
							<property name="AppsSortBy">lastused</property>
							<onclick>ActivateWindow(Programs,return)</onclick>
							<visible>System.Platform.Android</visible>
						</item>
						<item id="6">
							<label>$LOCALIZE[21452]</label>
							<icon>DefaultFolder.png</icon>
							<property name="AppsTarget">addonbrowser</property>
							<property name="AppsContent">addons://all</property>
							<property name="AppsSortBy"></property>
							<onclick>ActivateWindow(AddonBrowser,return)</onclick>
						</item>
					</content>
				</control>
			</control>
			<control type="group">
				<control type="group">
	                <visible>Integer.IsGreater(Container(51).NumItems,0)</visible>
	                <control type="image">
	                	<left>730</left>
	                    <top>180</top>
	                    <width>1100</width>
	                    <height>120</height>
	                    <visible>Control.HasFocus(51)</visible>
	                    <animation effect="fade" time="320" delay="200">Visible</animation>
	                    <animation effect="fade" time="50">Hidden</animation>
	                    <texture colordiffuse="$VAR[ColorHighlightVar]" border="5">listselect_fo.png</texture>
	                    <animation effect="slide" end="0,120" time="300" tween="cubic" easing="inout" condition="Integer.IsGreater(Container(51).Row,5)">Conditional</animation>
	                    <animation effect="slide" end="0,120" time="300" tween="cubic" easing="inout" condition="Integer.IsGreater(Container(51).Row,4)">Conditional</animation>
	                    <animation effect="slide" end="0,120" time="300" tween="cubic" easing="inout" condition="Integer.IsGreater(Container(51).Row,3)">Conditional</animation>
	                    <animation effect="slide" end="0,120" time="300" tween="cubic" easing="inout" condition="Integer.IsGreater(Container(51).Row,2)">Conditional</animation>
	                    <animation effect="slide" end="0,120" time="300" tween="cubic" easing="inout" condition="Integer.IsGreater(Container(51).Row,1)">Conditional</animation>
	                    <animation effect="slide" end="0,120" time="300" tween="cubic" easing="inout" condition="Integer.IsGreater(Container(51).Row,0)">Conditional</animation>
	                </control>
	            </control>
				<control type="panel" id="51">
					<left>730</left>
					<top>180</top>
					<width>1100</width>
					<height>840</height>
					<onleft>50</onleft>
					<onright condition="Container(51).HasNext | Container(51).HasPrevious">60</onright>
					<onup>51</onup>
					<ondown>51</ondown>
					<animation effect="fade" start="100" end="0" time="300" condition="Container(51).IsUpdating">conditional</animation>
					<viewtype label="535">list</viewtype>
					<pagecontrol>60</pagecontrol>
					<scrolltime tween="quadratic" easing="out">200</scrolltime>
					<itemlayout height="120" width="810">
						<control type="image">
							<left>10</left>
							<top>10</top>
							<width>100</width>
							<height>100</height>
							<aspectratio scalediffuse="false">keep</aspectratio>
							<texture background="true" diffuse="diffuse/list-icon.png" fallback="DefaultFolder.png">$INFO[ListItem.Icon]</texture>
						</control>
						<control type="label">
							<left>135</left>
							<top>3</top>
							<width>940</width>
							<height>70</height>
							<font>font30</font>
							<label>$INFO[ListItem.Label]</label>
						</control>
						<control type="label">
							<left>135</left>
							<top>52</top>
							<width>940</width>
							<height>60</height>
							<label>$INFO[ListItem.AddonSummary]</label>
						</control>
					</itemlayout>
					<focusedlayout height="120" width="810">
						<control type="image">
							<left>10</left>
							<top>10</top>
							<width>100</width>
							<height>100</height>
							<aspectratio scalediffuse="false">keep</aspectratio>
							<texture background="true" diffuse="diffuse/list-icon.png" fallback="DefaultFolder.png">$INFO[ListItem.Icon]</texture>
						</control>
						<control type="label">
							<left>135</left>
							<top>3</top>
							<width>940</width>
							<height>70</height>
							<font>font30</font>
							<label>$INFO[ListItem.Label]</label>
						</control>
						<control type="label">
							<left>135</left>
							<top>52</top>
							<width>940</width>
							<height>60</height>
							<label>$INFO[ListItem.AddonSummary]</label>
						</control>
					</focusedlayout>
					<content target="$INFO[Container(50).ListItem.Property(AppsTarget)]" sortby="$INFO[Container(50).ListItem.Property(AppsSortBy)]" sortorder="descending">$INFO[Container(50).ListItem.Property(AppsContent)]</content>
				</control>
				<control type="scrollbar" id="60">
					<visible allowhiddenfocus="true">Control.HasFocus(60) | Container(51).Scrolling</visible>
					<animation effect="fade" time="300" tween="sine" easing="inout" start="0" end="100">Visible</animation>
					<left>1910</left>
					<top>120</top>
					<width>10</width>
					<height>960</height>
					<onup>60</onup>
					<ondown>60</ondown>
					<onleft>51</onleft>
					<onright>51</onright>
					<orientation>vertical</orientation>
				</control>
			</control>
		</control>
		<include>Topbar</include>
	</controls>
</window>