<?xml version="1.0" encoding="utf-8"?>
<window>
	<defaultcontrol always="true">9000</defaultcontrol>
	<allowoverlay>no</allowoverlay>
	<onload>RunScript(script.skinshortcuts,type=buildxml&amp;mode=single&amp;options=clonewidgets&amp;mainmenuID=9000&amp;group=mainmenu|quicknav)</onload>
	<onload>ClearProperty(MediaMenu,Home)</onload>
    <onunload condition="!Skin.HasSetting(Enable.HorizontalMenu) + Skin.HasSetting(Enable.CombineMenus)">RunScript(script.skinshortcuts,type=hidesubmenu&amp;mainmenuID=9000)</onunload>
	<controls>
        <control type="wraplist" id="9034">
            <include>HiddenList</include>
            <content>$INFO[Container(9000).ListItem.Property(backgroundPlaylist)]</content>
            <autoscroll time="7000" delay="7000" repeat="7000">String.IsEqual(Container(9000).ListItem.Property(background),playlistBackground)</autoscroll>
            <visible>String.IsEqual(Container(9000).ListItem.Property(background),playlistBackground)</visible>
        </control>
 		<control type="multiimage">
            <fadetime>300</fadetime>
            <animation effect="fade" time="200" tween="cubic">Visible</animation>
            <include>FullscreenDimensions</include>
            <imagepath background="true">$VAR[HomeBackgroundVar]</imagepath>
        </control>
        <include>skinshortcuts-template-WidgetFanart</include>
        <control type="visualisation">
        	<visible>Player.HasAudio + !Skin.HasSetting(Disable.ShowBackgroundVis)</visible>
            <include>FullscreenDimensions</include>
        </control>
        <control type="group">
            <visible>Player.HasVideo + !Skin.HasSetting(Disable.ShowBackgroundVideo)</visible>
            <control type="image">
    			<include>FullscreenDimensions</include>
    			<texture>black.png</texture>
    		</control>
     		<control type="videowindow">
                <include>FullscreenDimensions</include>
            </control>
        </control>
        <control type="image">
            <include>FullscreenDimensions</include>
            <texture>background.png</texture>
            <colordiffuse>$VAR[ColorBackgroundVar]</colordiffuse>
        </control>
		<include>Topbar</include>
        <include condition="!Skin.HasSetting(Enable.HorizontalMenu)">HomeVertical</include>
		<include condition="Skin.HasSetting(Enable.HorizontalMenu)">HomeHorizontal</include>
	</controls>
</window>